MANIFEST.in
README.md
setup.py
bin/news-scraper
news_scraper/__init__.py
news_scraper/article.py
news_scraper/display.py
news_scraper/scrape.py
news_scraper/ui.py
news_scraper.egg-info/PKG-INFO
news_scraper.egg-info/SOURCES.txt
news_scraper.egg-info/dependency_links.txt
news_scraper.egg-info/not-zip-safe
news_scraper.egg-info/requires.txt
news_scraper.egg-info/top_level.txt