Metadata-Version: 1.1
Name: news-scraper
Version: 0.2.0
Summary: Generates short snippets of news articles
Home-page: http://github.com/mnkhouri/news_scraper
Author: Marc Khouri
Author-email: marc@khouri.ca
License: GPLv2
Keywords: news scraper
Platform: UNKNOWN
Classifier: Development Status :: 3 - Alpha
Classifier: Environment :: Console
Classifier: License :: OSI Approved :: GNU General Public License v2 (GPLv2)
Classifier: Programming Language :: Python :: 3 :: Only
